date_cli/__init__.py
date_cli/bin/__init__.py
date_cli-0.0.1.data/scripts/date_range
date_cli-0.0.1.data/scripts/month_range
date_cli-0.0.1.dist-info/METADATA
date_cli-0.0.1.dist-info/WHEEL
date_cli-0.0.1.dist-info/top_level.txt
date_cli-0.0.1.dist-info/RECORD
